LICENSE
transactid/cert.pem
transactid/dummy_keys.py
transactid/exceptions.py
transactid/google.pem
transactid/inter.pem
transactid/paymentrequest.proto
transactid/paymentrequest_pb2.py
transactid/requirements.txt
transactid/root.pem
transactid/transactid.py
transactid-0.1.0a3.dist-info/LICENSE
transactid-0.1.0a3.dist-info/WHEEL
transactid-0.1.0a3.dist-info/METADATA
transactid-0.1.0a3.dist-info/RECORD
