Metadata-Version: 2.1
Name: transactid
Version: 0.1.0a3
Summary: A package for working with BIP75 and BIP70 in a Python environment.
Home-page: https://github.com/netkicorp/transactid-library-python
License: BSD-3-Clause
Keywords: transactid,BIP75,BIP70
Author: Jeremy Kenyon
Author-email: jeremy@netki.com
Requires-Python: >=3.6.5,<4.0.0
Classifier: License :: OSI Approved :: BSD License
Classifier: Operating System :: OS Independent
Classifier: Programming Language :: Python :: 3
Classifier: Programming Language :: Python :: 3.7
Requires-Dist: certvalidator (>=0.11.1,<0.12.0)
Requires-Dist: cryptography (==2.7)
Requires-Dist: protobuf (==3.9.2)
Project-URL: Repository, https://github.com/netkicorp/transactid-library-python
